px/__init__.py
px/constants.py
px/main.py
px/core/__init__.py
px/core/template.py
px/subcmds/__init__.py
px/templates/README.md
px/templates/__init__.py
px/templates/pyameer.py
python_px-0.0.11.dist-info/METADATA
python_px-0.0.11.dist-info/WHEEL
python_px-0.0.11.dist-info/entry_points.txt
python_px-0.0.11.dist-info/licenses/LICENSE
python_px-0.0.11.dist-info/RECORD
