Metadata-Version: 2.3
Name: python-px
Version: 0.0.11
Summary: npx but for python
Project-URL: Repository, https://github.com/AmeerArsala/px
Project-URL: Source, https://github.com/AmeerArsala/px
Project-URL: Tracker, https://github.com/AmeerArsala/px/issues
Author-email: Ameer Arsala <ameer.arsala03@gmail.com>
License:                                  Apache License
License-File: LICENSE
Requires-Python: >=3.10
Requires-Dist: pydantic>2.0
Requires-Dist: rich<14,>=13.8.1
Requires-Dist: typer<0.13,>=0.12.5
